django_auto_timestamps_model/__init__.py
django_auto_timestamps_model/apps.py
django_auto_timestamps_model/models.py
django_auto_timestamps_model-1.0.0.dist-info/LICENSE
django_auto_timestamps_model-1.0.0.dist-info/METADATA
django_auto_timestamps_model-1.0.0.dist-info/WHEEL
django_auto_timestamps_model-1.0.0.dist-info/top_level.txt
django_auto_timestamps_model-1.0.0.dist-info/RECORD
