Metadata-Version: 2.1
Name: django-auto-timestamps-model
Version: 1.0.0
Summary: Django model for adding automatic timestamps in models.
Home-page: https://github.com/santiagopuerta/django-auto-timestamps-model
Author: Santiago
License: MIT
Platform: UNKNOWN
Classifier: Development Status :: 5 - Production/Stable
Classifier: Intended Audience :: Developers
Classifier: License :: OSI Approved :: MIT License
Classifier: Programming Language :: Python :: 3.11
Classifier: Framework :: Django
Classifier: Operating System :: OS Independent
License-File: LICENSE
Requires-Dist: Django (>=1.4)
